binance_chain/__init__.py
binance_chain/constants.py
binance_chain/depthcache.py
binance_chain/environment.py
binance_chain/exceptions.py
binance_chain/http.py
binance_chain/messages.py
binance_chain/wallet.py
binance_chain/websockets.py
binance_chain/ledger/__init__.py
binance_chain/ledger/client.py
binance_chain/ledger/exceptions.py
binance_chain/ledger/wallet.py
binance_chain/node_rpc/__init__.py
binance_chain/node_rpc/http.py
binance_chain/node_rpc/pooled_client.py
binance_chain/node_rpc/request.py
binance_chain/node_rpc/websockets.py
binance_chain/protobuf/__init__.py
binance_chain/protobuf/dex_pb2.py
binance_chain/signing/__init__.py
binance_chain/signing/http.py
binance_chain/utils/__init__.py
binance_chain/utils/encode_utils.py
binance_chain/utils/segwit_addr.py
tests/__init__.py
tests/test_client.py
tests/test_depthcache.py
tests/test_environment.py
tests/test_messages.py
tests/test_rpc_client.py
tests/test_rpc_pooled.py
tests/test_rpc_websockets.py
tests/test_signing.py
tests/test_utils.py
tests/test_wallet.py
tests/test_websockets.py
binancechainpy-0.1.25.dist-info/LICENSE
binancechainpy-0.1.25.dist-info/METADATA
binancechainpy-0.1.25.dist-info/WHEEL
binancechainpy-0.1.25.dist-info/top_level.txt
binancechainpy-0.1.25.dist-info/RECORD
